getstoken/__init__.py
getstoken/__main__.py
getstoken/parserkube.py
gettoken-1.0.2.dist-info/LICENSE
gettoken-1.0.2.dist-info/METADATA
gettoken-1.0.2.dist-info/WHEEL
gettoken-1.0.2.dist-info/dependency_links.txt
gettoken-1.0.2.dist-info/entry_points.txt
gettoken-1.0.2.dist-info/top_level.txt
gettoken-1.0.2.dist-info/RECORD
